LICENSE.txt
README.md
setup.cfg
setup.py
src/build_layout.py
src/check_for_salt.py
src/create_master_password_button_event.py
src/decrypt.py
src/derive_key.py
src/encrypt.py
src/enter_existing_master_password_button.py
src/enter_password_button_event.py
src/generate_key.py
src/generate_salt.py
src/insert_password.py
src/load_salt.py
src/main.py
src/show_form.py
src/show_password_button_event.py
src/password_manager_py.egg-info/PKG-INFO
src/password_manager_py.egg-info/SOURCES.txt
src/password_manager_py.egg-info/dependency_links.txt
src/password_manager_py.egg-info/requires.txt
src/password_manager_py.egg-info/top_level.txt