Metadata-Version: 2.1
Name: password-manager-py
Version: 1.1.0
Author: SMc
Author-email: jackagusjill21@gmail.com
Keywords: password manager
License-File: LICENSE.txt
